smart_api_integrations/__init__.py
smart_api_integrations/py.typed
smart_api_integrations/cli/__init__.py
smart_api_integrations/cli/__main__.py
smart_api_integrations/cli/main.py
smart_api_integrations/cli/openapi_converter.py
smart_api_integrations/cli/commands/__init__.py
smart_api_integrations/cli/commands/add_endpoints.py
smart_api_integrations/cli/commands/add_provider.py
smart_api_integrations/cli/commands/add_webhook.py
smart_api_integrations/cli/commands/generate_client.py
smart_api_integrations/cli/commands/generate_type_stubs.py
smart_api_integrations/cli/commands/generate_webhook_handler.py
smart_api_integrations/cli/commands/openapi_to_config.py
smart_api_integrations/cli/commands/smart_api_test.py
smart_api_integrations/cli/commands/test_webhook.py
smart_api_integrations/clients/__init__.py
smart_api_integrations/clients/github.py
smart_api_integrations/clients/hubspot.py
smart_api_integrations/clients/universal.py
smart_api_integrations/core/__init__.py
smart_api_integrations/core/auth.py
smart_api_integrations/core/client.py
smart_api_integrations/core/loader.py
smart_api_integrations/core/registry.py
smart_api_integrations/core/response_adapter.py
smart_api_integrations/core/schema.py
smart_api_integrations/core/webhook.py
smart_api_integrations/core/webhook_registry.py
smart_api_integrations/core/webhook_schema.py
smart_api_integrations/frameworks/__init__.py
smart_api_integrations/frameworks/django.py
smart_api_integrations/frameworks/fastapi.py
smart_api_integrations/frameworks/flask.py
smart_api_integrations/providers/example/webhook.yaml
smart_api_integrations/providers/github/config.yaml
smart_api_integrations/providers/github/webhook.yaml
smart_api_integrations/providers/petstore/openapi.yaml
smart_api_integrations/webhooks/__init__.py
smart_api_integrations/webhooks/base.py
smart_api_integrations/webhooks/decorators.py
smart_api_integrations/webhooks/handlers.py
smart_api_integrations/webhooks/server.py
smart_api_integrations-0.2.0.dist-info/licenses/LICENSE
smart_api_integrations-0.2.0.dist-info/METADATA
smart_api_integrations-0.2.0.dist-info/WHEEL
smart_api_integrations-0.2.0.dist-info/entry_points.txt
smart_api_integrations-0.2.0.dist-info/top_level.txt
smart_api_integrations-0.2.0.dist-info/RECORD
