Metadata-Version: 2.4
Name: smart-api-integrations
Version: 0.2.0
Summary: Connect to any API and receive webhooks with minimal code. Turn API docs into Python functions and handle incoming events easily.
Author-email: Ananda Behera <behera.anand1@gmail.com>
Maintainer-email: Ananda Behera <behera.anand1@gmail.com>
License-Expression: MIT
Project-URL: Homepage, https://github.com/behera116/smart-api-integrations
Project-URL: Documentation, https://github.com/behera116/smart-api-integrations/tree/main/docs
Project-URL: Repository, https://github.com/behera116/smart-api-integrations
Project-URL: Bug Tracker, https://github.com/behera116/smart-api-integrations/issues
Project-URL: Changelog, https://github.com/behera116/smart-api-integrations/blob/main/CHANGELOG.md
Keywords: api,integration,webhook,client,rest,automation,sdk,http,requests,type-safe,cli
Classifier: Development Status :: 5 - Production/Stable
Classifier: Intended Audience :: Developers
Classifier: Operating System :: OS Independent
Classifier: Programming Language :: Python :: 3
Classifier: Programming Language :: Python :: 3.8
Classifier: Programming Language :: Python :: 3.9
Classifier: Programming Language :: Python :: 3.10
Classifier: Programming Language :: Python :: 3.11
Classifier: Programming Language :: Python :: 3.12
Classifier: Topic :: Software Development :: Libraries :: Python Modules
Classifier: Topic :: Internet :: WWW/HTTP
Classifier: Topic :: Software Development :: Code Generators
Classifier: Typing :: Typed
Requires-Python: >=3.8
License-File: LICENSE
Requires-Dist: httpx>=0.23.0
Requires-Dist: pyyaml>=6.0
Requires-Dist: requests>=2.28.0
Requires-Dist: pydantic<3.0.0,>=1.8.0
Requires-Dist: click>=8.0.0
Provides-Extra: django
Requires-Dist: django>=3.2.0; extra == "django"
Provides-Extra: flask
Requires-Dist: flask>=2.0.0; extra == "flask"
Provides-Extra: fastapi
Requires-Dist: fastapi>=0.68.0; extra == "fastapi"
Requires-Dist: uvicorn>=0.15.0; extra == "fastapi"
Provides-Extra: ai
Requires-Dist: openai>=1.0.0; extra == "ai"
Provides-Extra: dev
Requires-Dist: pytest>=7.0.0; extra == "dev"
Requires-Dist: pytest-cov>=4.0.0; extra == "dev"
Requires-Dist: black>=22.0.0; extra == "dev"
Requires-Dist: isort>=5.10.0; extra == "dev"
Requires-Dist: mypy>=1.0.0; extra == "dev"
Requires-Dist: pre-commit>=2.20.0; extra == "dev"
Requires-Dist: twine>=4.0.0; extra == "dev"
Requires-Dist: build>=0.8.0; extra == "dev"
Provides-Extra: test
Requires-Dist: pytest>=7.0.0; extra == "test"
Requires-Dist: pytest-cov>=4.0.0; extra == "test"
Requires-Dist: pytest-mock>=3.10.0; extra == "test"
Requires-Dist: responses>=0.22.0; extra == "test"
Provides-Extra: docs
Requires-Dist: mkdocs>=1.4.0; extra == "docs"
Requires-Dist: mkdocs-material>=8.5.0; extra == "docs"
Requires-Dist: mkdocstrings[python]>=0.19.0; extra == "docs"
Provides-Extra: all
Requires-Dist: smart-api-integrations[ai,django,fastapi,flask]; extra == "all"
Dynamic: license-file
